NuMPI/MPIStub.py
NuMPI/__init__.py
NuMPI/IO/NPY.py
NuMPI/IO/__init__.py
NuMPI/IO/common.py
NuMPI/Optimization/CCGWithRestart.py
NuMPI/Optimization/CCGWithoutRestart.py
NuMPI/Optimization/LBFGS.py
NuMPI/Optimization/LineSearch.py
NuMPI/Optimization/Result.py
NuMPI/Optimization/Wolfe.py
NuMPI/Optimization/__init__.py
NuMPI/Testing/Assertions.py
NuMPI/Testing/Fixtures.py
NuMPI/Testing/Subdivision.py
NuMPI/Tools/Reduction.py
NuMPI/Tools/Subdivision.py
NuMPI/Tools/__init__.py
numpi-0.8.3.dist-info/licenses/LICENSE.md
numpi-0.8.3.dist-info/WHEEL
numpi-0.8.3.dist-info/METADATA
numpi-0.8.3.dist-info/RECORD
