Metadata-Version: 2.4
Name: NuMPI
Version: 0.8.3
Summary: Numerical tools for MPI-parallelized code
Author-email: Antoine Sanner <antoine.sanner@imtek.uni-freiburg.de>, Lars Pastewka <lars.pastewka@imtek.uni-freiburg.de>
Requires-Python: >=3.8.0
Classifier: Development Status :: 5 - Production/Stable
Classifier: Programming Language :: Python
License-File: LICENSE.md
Requires-Dist: DiscoverVersion
Requires-Dist: scipy>1.1.0
Requires-Dist: primefac
Requires-Dist: mpi4py ; extra == "mpi"
Requires-Dist: flake8<5 ; extra == "test"
Requires-Dist: pytest ; extra == "test"
Requires-Dist: pytest-cov ; extra == "test"
Requires-Dist: pytest-flake8 ; extra == "test"
Project-URL: changelog, https://github.com/IMTEK-Simulation/NuMPI/blob/master/ChangeLog.md
Project-URL: repository, https://github.com/IMTEK-Simulation/NuMPI
Provides-Extra: mpi
Provides-Extra: test
